tbcontrol/__init__.py
tbcontrol/blocksim.py
tbcontrol/controllers.py
tbcontrol/conversion.py
tbcontrol/fopdtitae.py
tbcontrol/loops.py
tbcontrol/numeric.py
tbcontrol/plotting.py
tbcontrol/responses.py
tbcontrol/symbolic.py
tbcontrol/version.py
tbcontrol-0.2.1.dist-info/LICENSE
tbcontrol-0.2.1.dist-info/METADATA
tbcontrol-0.2.1.dist-info/WHEEL
tbcontrol-0.2.1.dist-info/top_level.txt
tbcontrol-0.2.1.dist-info/RECORD
