Metadata-Version: 2.1
Name: tbcontrol
Version: 0.2.1
Summary: Textbook Control Problem package
Home-page: https://github.com/alchemyst/Dynamics-and-Control
Author: Carl Sandrock
Author-email: carl.sandrock@gmail.com
License: UNKNOWN
Platform: UNKNOWN
Classifier: Programming Language :: Python :: 3
Classifier: License :: OSI Approved :: GNU General Public License v3 (GPLv3)
Classifier: Operating System :: OS Independent
Classifier: Intended Audience :: Education
Requires-Python: >=3.5
Requires-Dist: numpy
Requires-Dist: scipy
Requires-Dist: tqdm
Requires-Dist: packaging
